py_setup_tool/__init__.py
py_setup_tool/example.py
py_setup_tool-0.0.2.dist-info/licenses/LICENSE
py_setup_tool-0.0.2.dist-info/METADATA
py_setup_tool-0.0.2.dist-info/WHEEL
py_setup_tool-0.0.2.dist-info/top_level.txt
py_setup_tool-0.0.2.dist-info/RECORD
